fastapi_sa_orm_filter/__init__.py
fastapi_sa_orm_filter/dto.py
fastapi_sa_orm_filter/exceptions.py
fastapi_sa_orm_filter/interfaces.py
fastapi_sa_orm_filter/main.py
fastapi_sa_orm_filter/operators.py
fastapi_sa_orm_filter/parsers.py
fastapi_sa_orm_filter/sa_expression_builder.py
fastapi_sa_orm_filter-0.2.4.dist-info/licenses/LICENSE
fastapi_sa_orm_filter-0.2.4.dist-info/WHEEL
fastapi_sa_orm_filter-0.2.4.dist-info/METADATA
fastapi_sa_orm_filter-0.2.4.dist-info/RECORD
