Metadata-Version: 2.4
Name: fastapi-sa-orm-filter
Version: 0.2.4
Summary: FastAPI-SQLAlchemy filter, transform request query string to SQLAlchemy orm query
Author-email: Oleksandr Zhydyk <zhydykalex@ukr.net>
Requires-Python: >=3.10
Classifier: License :: OSI Approved :: MIT License
License-File: LICENSE
Requires-Dist: fastapi
Requires-Dist: sqlalchemy
Requires-Dist: pydantic
Requires-Dist: sqlalchemy-to-pydantic
Project-URL: Home, https://github.com/OleksandrZhydyk/FastAPI-SQLAlchemy-Filters
Project-URL: Issues, https://github.com/OleksandrZhydyk/FastAPI-SQLAlchemy-Filters/issues
